pyswitcheo/__init__.py
pyswitcheo/api.py
pyswitcheo/crypto_utils.py
pyswitcheo/errors.py
pyswitcheo/schemas.py
pyswitcheo/serialization.py
pyswitcheo/utils.py
pyswitcheo/datatypes/__init__.py
pyswitcheo/datatypes/fixed8.py
pyswitcheo/datatypes/transaction_types.py
pyswitcheo/internal/__init__.py
pyswitcheo/internal/api/__init__.py
pyswitcheo/internal/api/balances.py
pyswitcheo/internal/api/contracts.py
pyswitcheo/internal/api/deposits.py
pyswitcheo/internal/api/exchange.py
pyswitcheo/internal/api/offers.py
pyswitcheo/internal/api/orders.py
pyswitcheo/internal/api/pairs.py
pyswitcheo/internal/api/tickers.py
pyswitcheo/internal/api/trades.py
pyswitcheo/internal/api/withdrawals.py
pyswitcheo/internal/urls/__init__.py
pyswitcheo/internal/urls/address.py
pyswitcheo/internal/urls/amounts.py
pyswitcheo/internal/urls/balances.py
pyswitcheo/internal/urls/base.py
pyswitcheo/internal/urls/contracts.py
pyswitcheo/internal/urls/deposits.py
pyswitcheo/internal/urls/exchange.py
pyswitcheo/internal/urls/offers.py
pyswitcheo/internal/urls/orders.py
pyswitcheo/internal/urls/pairs.py
pyswitcheo/internal/urls/tickers.py
pyswitcheo/internal/urls/trades.py
pyswitcheo/internal/urls/withdrawals.py
pyswitcheo-0.1.1.dist-info/METADATA
pyswitcheo-0.1.1.dist-info/RECORD
pyswitcheo-0.1.1.dist-info/WHEEL
pyswitcheo-0.1.1.dist-info/top_level.txt
