Metadata-Version: 2.1
Name: pyswitcheo
Version: 0.1.1
Summary: Python library to interact with switcheo APIs
Home-page: UNKNOWN
Author: Ankur Srivastava
Author-email: best.ankur@gmail.com
License: UNKNOWN
Download-URL: https://github.com/ansrivas/pyswitcheo/archive/0.1.1.tar.gz
Platform: UNKNOWN
Classifier: Programming Language :: Python :: 3.6
Classifier: Programming Language :: Python :: 3.7
Requires-Dist: requests (==2.19.1)
Requires-Dist: neocore
Requires-Dist: jsonschema (==2.6.0)
